meridianalgo/__init__.py
meridianalgo/advanced_risk.py
meridianalgo/algorithmic_trading.py
meridianalgo/alternative_assets.py
meridianalgo/api.py
meridianalgo/config.py
meridianalgo/core.py
meridianalgo/crypto.py
meridianalgo/crypto_expanded.py
meridianalgo/derivatives.py
meridianalgo/diversification.py
meridianalgo/fixed_income.py
meridianalgo/forex.py
meridianalgo/statistics.py
meridianalgo/analytics/__init__.py
meridianalgo/analytics/attribution.py
meridianalgo/analytics/drawdown.py
meridianalgo/analytics/performance.py
meridianalgo/analytics/risk_analytics.py
meridianalgo/analytics/tear_sheets.py
meridianalgo/backtesting/__init__.py
meridianalgo/backtesting/advanced.py
meridianalgo/backtesting/backtester.py
meridianalgo/backtesting/engine.py
meridianalgo/backtesting/event_driven.py
meridianalgo/backtesting/events.py
meridianalgo/backtesting/market_simulator.py
meridianalgo/backtesting/order_management.py
meridianalgo/backtesting/performance_analytics.py
meridianalgo/backtesting/visualization/__init__.py
meridianalgo/computing/distributed.py
meridianalgo/core/__init__.py
meridianalgo/core/portfolio/__init__.py
meridianalgo/core/portfolio/optimization.py
meridianalgo/core/risk/__init__.py
meridianalgo/core/risk/metrics.py
meridianalgo/core/statistics/__init__.py
meridianalgo/core/time_series/__init__.py
meridianalgo/core/time_series/analysis.py
meridianalgo/data/__init__.py
meridianalgo/data/exceptions.py
meridianalgo/data/free_providers.py
meridianalgo/data/models.py
meridianalgo/data/processing.py
meridianalgo/data/providers.py
meridianalgo/data/storage.py
meridianalgo/data/streaming.py
meridianalgo/data/datasets/__init__.py
meridianalgo/data/loaders/__init__.py
meridianalgo/data/processors/__init__.py
meridianalgo/docs/source/conf.py
meridianalgo/fixed_income/bonds.py
meridianalgo/fixed_income/options.py
meridianalgo/liquidity/__init__.py
meridianalgo/liquidity/impact.py
meridianalgo/liquidity/metrics.py
meridianalgo/liquidity/microstructure.py
meridianalgo-6.2.1.dist-info/METADATA
meridianalgo-6.2.1.dist-info/WHEEL
meridianalgo-6.2.1.dist-info/entry_points.txt
meridianalgo-6.2.1.dist-info/top_level.txt
meridianalgo-6.2.1.dist-info/RECORD
