Metadata-Version: 2.4
Name: meridianalgo
Version: 6.2.1
Summary: MeridianAlgo - The Complete Quantitative Finance Platform for Professional Developers
Home-page: https://github.com/MeridianAlgo/Python-Packages
Author: Meridian Algorithmic Research Team
Author-email: Meridian Algorithmic Research Team <support@meridianalgo.com>
License: MIT
Project-URL: Bug Reports, https://github.com/MeridianAlgo/Python-Packages/issues
Project-URL: Source, https://github.com/MeridianAlgo/Python-Packages
Project-URL: Documentation, https://meridianalgo.readthedocs.io
Project-URL: Changelog, https://github.com/MeridianAlgo/Python-Packages/blob/main/CHANGELOG.md
Keywords: quantitative-finance,algorithmic-trading,trading,finance,portfolio-optimization,risk-management,portfolio-analytics,execution-algorithms,vwap,twap,market-impact,market-microstructure,liquidity,order-book,statistical-arbitrage,pairs-trading,mean-reversion,factor-models,options-pricing,high-frequency-trading,regime-detection,machine-learning
Classifier: Development Status :: 5 - Production/Stable
Classifier: Programming Language :: Python :: 3
Classifier: Programming Language :: Python :: 3.8
Classifier: Programming Language :: Python :: 3.9
Classifier: Programming Language :: Python :: 3.10
Classifier: Programming Language :: Python :: 3.11
Classifier: Programming Language :: Python :: 3.12
Classifier: License :: OSI Approved :: MIT License
Classifier: Operating System :: OS Independent
Classifier: Intended Audience :: Financial and Insurance Industry
Classifier: Intended Audience :: Science/Research
Classifier: Intended Audience :: Developers
Classifier: Topic :: Office/Business :: Financial :: Investment
Classifier: Topic :: Scientific/Engineering :: Mathematics
Classifier: Topic :: Scientific/Engineering :: Artificial Intelligence
Classifier: Typing :: Typed
Requires-Python: >=3.10
Requires-Dist: numpy>=1.24.0
Requires-Dist: pandas>=2.0.0
Requires-Dist: scipy>=1.10.0
Requires-Dist: yfinance>=0.2.30
Requires-Dist: requests>=2.31.0
Requires-Dist: matplotlib>=3.7.0
Requires-Dist: seaborn>=0.12.0
Requires-Dist: ta>=0.11.0
Requires-Dist: tqdm>=4.66.0
Requires-Dist: joblib>=1.3.0
Requires-Dist: python-dateutil>=2.8.2
Requires-Dist: pytz>=2023.3
Provides-Extra: dev
Requires-Dist: pytest>=7.4.0; extra == "dev"
Requires-Dist: pytest-cov>=4.1.0; extra == "dev"
Requires-Dist: pytest-xdist>=3.3.0; extra == "dev"
Requires-Dist: ruff>=0.1.0; extra == "dev"
Requires-Dist: black>=23.9.0; extra == "dev"
Requires-Dist: isort>=5.12.0; extra == "dev"
Requires-Dist: mypy>=1.5.0; extra == "dev"
Requires-Dist: sphinx>=7.0.0; extra == "dev"
Requires-Dist: sphinx-rtd-theme>=1.3.0; extra == "dev"
Provides-Extra: ml
Requires-Dist: scikit-learn>=1.3.0; extra == "ml"
Requires-Dist: torch>=2.1.0; extra == "ml"
Requires-Dist: statsmodels>=0.14.0; extra == "ml"
Requires-Dist: hmmlearn>=0.3.0; extra == "ml"
Provides-Extra: optimization
Requires-Dist: cvxpy>=1.4.0; extra == "optimization"
Requires-Dist: cvxopt>=1.3.0; extra == "optimization"
Provides-Extra: volatility
Requires-Dist: arch>=6.2.0; extra == "volatility"
Provides-Extra: data
Requires-Dist: lxml>=4.9.0; extra == "data"
Requires-Dist: beautifulsoup4>=4.12.0; extra == "data"
Requires-Dist: polygon-api-client>=1.12.0; extra == "data"
Provides-Extra: distributed
Requires-Dist: ray>=2.7.0; extra == "distributed"
Requires-Dist: dask>=2023.10.0; extra == "distributed"
Provides-Extra: full
Requires-Dist: scikit-learn>=1.3.0; extra == "full"
Requires-Dist: torch>=2.1.0; extra == "full"
Requires-Dist: statsmodels>=0.14.0; extra == "full"
Requires-Dist: hmmlearn>=0.3.0; extra == "full"
Requires-Dist: cvxpy>=1.4.0; extra == "full"
Requires-Dist: arch>=6.2.0; extra == "full"
Requires-Dist: lxml>=4.9.0; extra == "full"
Requires-Dist: beautifulsoup4>=4.12.0; extra == "full"
Provides-Extra: all
Requires-Dist: scikit-learn>=1.3.0; extra == "all"
Requires-Dist: torch>=2.1.0; extra == "all"
Requires-Dist: statsmodels>=0.14.0; extra == "all"
Requires-Dist: hmmlearn>=0.3.0; extra == "all"
Requires-Dist: cvxpy>=1.4.0; extra == "all"
Requires-Dist: cvxopt>=1.3.0; extra == "all"
Requires-Dist: arch>=6.2.0; extra == "all"
Requires-Dist: lxml>=4.9.0; extra == "all"
Requires-Dist: beautifulsoup4>=4.12.0; extra == "all"
Requires-Dist: polygon-api-client>=1.12.0; extra == "all"
Requires-Dist: ray>=2.7.0; extra == "all"
Dynamic: author
Dynamic: home-page
Dynamic: requires-python
